cis_DjangoSignUp/__init__.py
cis_DjangoSignUp/context_processors.py
cis_DjangoSignUp/forms.py
cis_DjangoSignUp/url.py
cis_DjangoSignUp/views.py
cis_DjangoSignUp/static/css/registration_form.css
cis_DjangoSignUp/static/js/Bootstrap_notify.js
cis_DjangoSignUp/static/js/notify.js
cis_DjangoSignUp/templates/cis_DjangoSignUp/acc_active_email.html
cis_DjangoSignUp/templates/cis_DjangoSignUp/registration_form.html
cis_DjangoSignUp-0.0.4.dist-info/DESCRIPTION.rst
cis_DjangoSignUp-0.0.4.dist-info/METADATA
cis_DjangoSignUp-0.0.4.dist-info/RECORD
cis_DjangoSignUp-0.0.4.dist-info/WHEEL
cis_DjangoSignUp-0.0.4.dist-info/metadata.json
cis_DjangoSignUp-0.0.4.dist-info/top_level.txt
