Metadata-Version: 2.0
Name: cis-DjangoSignUp
Version: 0.0.4
Summary: A simple Django app to conduct Web-based polls.
Home-page: UNKNOWN
Author: harish r
Author-email: harish.r@imailt.com
License: BSD License
Platform: UNKNOWN
Classifier: Environment :: Web Environment
Classifier: Framework :: Django
Classifier: Intended Audience :: Developers
Classifier: License :: OSI Approved :: BSD License
Classifier: Operating System :: OS Independent
Classifier: Programming Language :: Python
Classifier: Programming Language :: Python :: 3
Classifier: Programming Language :: Python :: 3.4
Classifier: Programming Language :: Python :: 3.5
